{
  "category": {
    "code": "ARTICLEFEATURE",
    "name": {
      "en": "Feature article"
    }
  },
  "channel": {},
  "contributors": {
    "url": "https://api.cristin.no/v2/results/2368072/contributors",
    "count": 2,
    "preview": [
      {
        "first_name": "Kjerstin",
        "surname": "Aukrust"
      },
      {
        "first_name": "Jonas",
        "surname": "Dræge"
      }
    ]
  },
  "cristin_result_id": "2368072",
  "nva_result_id": "0198cc3e7ce1-3cfb71df-d2ff-45de-9f84-6e898e90463f",
  "created": {
    "date": "2025-08-21T10:48:24.000Z"
  },
  "last_modified": {
    "date": "2025-10-13T10:41:39.000Z"
  },
  "date_published": "2025-02-19T00:00:00.000Z",
  "original_language": "nb",
  "title": {
    "nb": "Frankrikes rolle i Syria: Fra koloniherre til gjenoppbygger"
  },
  "year_published": "2025",
  "url": "https://api.cristin.no/v2/results/2368072",
  "journal": {}
}