{
  "category": {
    "code": "ACADEMICLECTURE",
    "name": {
      "en": "Academic lecture"
    }
  },
  "contributors": {
    "url": "https://api.cristin.no/v2/results/1977676/contributors",
    "count": 1,
    "preview": [
      {
        "first_name": "Ella Marie",
        "surname": "Sandbakken"
      }
    ]
  },
  "cristin_result_id": "1977676",
  "nva_result_id": "0198cc4f2928-9c6ef9f6-be20-4474-9428-5c2e9daac86b",
  "created": {
    "date": "2025-08-21T11:06:36.000Z"
  },
  "last_modified": {
    "date": "2025-10-11T16:12:33.000Z"
  },
  "original_language": "en",
  "title": {
    "en": "“If I Am to Open Up About My Life, I First Have to Put On My Emotional Armour”: A Qualitative Study on Living in Polyamorous Relationships in a Culture of Monogamy."
  },
  "year_published": "2021",
  "url": "https://api.cristin.no/v2/results/1977676",
  "event": {
    "name": "The 11th European Conference on Community Psychology",
    "location": "Oslo, Norway",
    "date_from": "2021-06-03T00:00:00.000Z",
    "date_to": "2021-06-04T00:00:00.000Z",
    "arranged_by": {
      "name": "The European Community Psychology Association (ECPA)"
    }
  }
}