{
  "category": {
    "code": "ACADEMICLECTURE",
    "name": {
      "en": "Academic lecture"
    }
  },
  "contributors": {
    "url": "https://api.cristin.no/v2/results/2363170/contributors",
    "count": 1,
    "preview": [
      {
        "first_name": "Ella Marie",
        "surname": "Sandbakken"
      }
    ]
  },
  "cristin_result_id": "2363170",
  "nva_result_id": "0198cc4dda05-50e31022-ffd0-4a3c-86ff-573b380e5465",
  "created": {
    "date": "2025-08-21T11:05:10.000Z"
  },
  "last_modified": {
    "date": "2025-10-13T16:50:22.000Z"
  },
  "original_language": "en",
  "title": {
    "en": "Narrative Negotiations of Compliance with COVID-19 Measures in Ecuador"
  },
  "year_published": "2024",
  "url": "https://api.cristin.no/v2/results/2363170",
  "event": {
    "name": "Dismantling Democracy: Insecurity, emotions and authoritarian populism  ISPP's 2024 Annual Meeting",
    "location": "Santiago, Chile",
    "date_from": "2024-07-04T00:00:00.000Z",
    "date_to": "2024-07-06T00:00:00.000Z",
    "arranged_by": {
      "name": "International Society of Political Psychology (ISPP)"
    }
  }
}