{
  "category": {
    "code": "ARTICLEFEATURE",
    "name": {
      "en": "Feature article"
    }
  },
  "channel": {},
  "contributors": {
    "url": "https://api.cristin.no/v2/results/1898303/contributors",
    "count": 3,
    "preview": [
      {
        "first_name": "Morten",
        "surname": "Holmboe"
      },
      {
        "first_name": "Hjørdis Birgitte",
        "surname": "Ellefsen"
      },
      {
        "first_name": "Brita",
        "surname": "Bjørkelo"
      }
    ]
  },
  "cristin_result_id": "1898303",
  "nva_result_id": "0198cc3c838a-a799d444-1392-4140-8858-e3faceb9a475",
  "created": {
    "date": "2025-08-21T10:46:14.000Z"
  },
  "last_modified": {
    "date": "2025-10-14T03:09:59.000Z"
  },
  "date_published": "2021-03-16T00:00:00.000Z",
  "links": [
    {
      "url_type": "FULLTEKST",
      "url": "https://www.politiforum.no/phs-politihogskolen/ingen-motsetning-mellom-autonomi-og-samhandling/211797"
    }
  ],
  "original_language": "nb",
  "summary": {
    "nb": "Høyere utdanning er regulert ved demokratisk vedtatte regler. Politihøgskolen har ikke mer autonomi enn andre høyskoler. Men heller ikke mindre."
  },
  "title": {
    "nb": "Ingen motsetning mellom autonomi og samhandling"
  },
  "year_published": "2021",
  "url": "https://api.cristin.no/v2/results/1898303",
  "journal": {}
}