{
  "category": {
    "code": "ACADEMICLECTURE",
    "name": {
      "en": "Academic lecture"
    }
  },
  "contributors": {
    "url": "https://api.cristin.no/v2/results/2269833/contributors",
    "count": 4,
    "preview": [
      {
        "first_name": "Brita",
        "surname": "Bjørkelo"
      },
      {
        "first_name": "Nina",
        "surname": "Sunde"
      },
      {
        "first_name": "Laura Vom",
        "surname": "Kolke"
      },
      {
        "first_name": "Piotr",
        "surname": "Wegorowski"
      }
    ]
  },
  "cristin_result_id": "2269833",
  "nva_result_id": "0198cc8efc7e-f96f4b26-880d-4b5b-8e88-9af6bcf7db89",
  "created": {
    "date": "2025-08-21T12:16:19.000Z"
  },
  "funding_sources": [
    {
      "funding_source_code": "EC/HEU",
      "project_code": "101121182",
      "funding_source_name": {
        "nb": "EU – Horisont Europa (EC/HEU)",
        "en": "EU – Horizon Europe (EC/HEU)"
      }
    }
  ],
  "last_modified": {
    "date": "2025-10-12T04:40:17.000Z"
  },
  "links": [
    {
      "url_type": "SAMMENDRAG",
      "url": "https://www.linkedin.com/company/claruseu/"
    },
    {
      "url_type": "OMTALE",
      "url": "https://www.linkedin.com/company/claruseu/"
    }
  ],
  "original_language": "en",
  "projects": [
    {
      "cristin_project_id": "2626838",
      "url": "https://api.cristin.no/v2/projects/2626838"
    }
  ],
  "title": {
    "en": "WP2 – Exploring Cultures, communication and interaction"
  },
  "year_published": "2024",
  "url": "https://api.cristin.no/v2/results/2269833",
  "event": {
    "name": "Clarus project meeting",
    "location": "The Adam Smith Business School",
    "date_from": "2024-04-17T00:00:00.000Z",
    "arranged_by": {
      "name": "Clarus"
    }
  }
}