{
  "category": {
    "code": "ARTICLE",
    "name": {
      "en": "Academic article"
    }
  },
  "channel": {
    "title": "Internasjonal Politikk"
  },
  "contributors": {
    "url": "https://api.cristin.no/v2/results/2130554/contributors",
    "count": 1,
    "preview": [
      {
        "first_name": "Hilde Eliassen",
        "surname": "Restad"
      }
    ]
  },
  "cristin_result_id": "2130554",
  "nva_result_id": "0198cc869665-273d5d84-49a9-478c-8a4d-170509a4295c",
  "created": {
    "date": "2025-08-21T12:07:09.000Z"
  },
  "last_modified": {
    "date": "2025-10-13T15:34:26.000Z"
  },
  "links": [
    {
      "url_type": "DOI",
      "url": "https://doi.org/10.23865/intpol.v79.2759"
    }
  ],
  "original_language": "nb",
  "title": {
    "nb": "Introduksjonsessay til fokusnummer: Hva nå, USA?"
  },
  "year_published": "2021",
  "url": "https://api.cristin.no/v2/results/2130554",
  "journal": {
    "cristin_journal_id": "6F6C9537-9C38-4B94-BE31-C5345BAC6CB5",
    "name": "Internasjonal Politikk",
    "international_standard_numbers": [
      {
        "type": "printed",
        "value": "0020-577X"
      },
      {
        "type": "electronic",
        "value": "1891-1757"
      }
    ],
    "nvi_level": "1",
    "external_url": "https://kanalregister.hkdir.no/publiseringskanaler/info/tidsskrift?pid=6F6C9537-9C38-4B94-BE31-C5345BAC6CB5"
  }
}