{
  "category": {
    "code": "ARTICLEPOPULAR",
    "name": {
      "en": "Popular scientific article"
    }
  },
  "channel": {
    "title": "Psykologisk.no"
  },
  "contributors": {
    "url": "https://api.cristin.no/v2/results/1995028/contributors",
    "count": 1,
    "preview": [
      {
        "first_name": "Ingvild",
        "surname": "Sagberg"
      }
    ]
  },
  "cristin_result_id": "1995028",
  "nva_result_id": "0198cc648491-c3f40e18-7236-46bb-9636-71f45e7bd0e7",
  "created": {
    "date": "2025-08-21T11:29:56.000Z"
  },
  "last_modified": {
    "date": "2025-10-13T16:02:57.000Z"
  },
  "original_language": "nb",
  "title": {
    "nb": "Medseilere"
  },
  "year_published": "2021",
  "url": "https://api.cristin.no/v2/results/1995028",
  "journal": {
    "cristin_journal_id": "EBDE44DD-DE8C-4CBA-A63B-61E8D0A8E0F9",
    "name": "Psykologisk.no",
    "external_url": "https://kanalregister.hkdir.no/publiseringskanaler/info/nvakanal?pid=EBDE44DD-DE8C-4CBA-A63B-61E8D0A8E0F9"
  }
}