{
  "category": {
    "code": "ARTICLE",
    "name": {
      "en": "Academic article"
    }
  },
  "channel": {
    "title": "Frontiers in Public Health"
  },
  "contributors": {
    "url": "https://api.cristin.no/v2/results/2190830/contributors",
    "count": 7,
    "preview": [
      {
        "first_name": "Sameer",
        "surname": "Bhargava"
      },
      {
        "first_name": "Edoardo",
        "surname": "Botteri"
      },
      {
        "first_name": "Mona",
        "surname": "Berthelsen"
      },
      {
        "first_name": "Nadia",
        "surname": "Iqbal"
      },
      {
        "first_name": "Kristin Ranheim",
        "surname": "Randel"
      },
      {
        "first_name": "Øyvind",
        "surname": "Holme"
      }
    ]
  },
  "cristin_result_id": "2190830",
  "nva_result_id": "0198cc514249-a3ca002a-4ddc-44c7-a4ab-950e0d4261eb",
  "created": {
    "date": "2025-08-21T11:08:54.000Z"
  },
  "import_sources": [
    {
      "source_name": "SCOPUS",
      "source_reference_id": "2-s2.0-85173792283"
    }
  ],
  "last_modified": {
    "date": "2025-10-13T15:57:20.000Z"
  },
  "links": [
    {
      "url_type": "DOI",
      "url": "https://doi.org/10.3389/fpubh.2023.1254905"
    },
    {
      "url_type": "ARKIV",
      "url": "https://hdl.handle.net/10852/109699"
    }
  ],
  "original_language": "en",
  "title": {
    "en": "Lower participation among immigrants in colorectal cancer screening in Norway"
  },
  "year_published": "2023",
  "url": "https://api.cristin.no/v2/results/2190830",
  "journal": {
    "cristin_journal_id": "778C1537-B3D6-462E-A475-632E387E7E45",
    "name": "Frontiers in Public Health",
    "international_standard_numbers": [
      {
        "type": "electronic",
        "value": "2296-2565"
      }
    ],
    "nvi_level": "1",
    "external_url": "https://kanalregister.hkdir.no/publiseringskanaler/info/tidsskrift?pid=778C1537-B3D6-462E-A475-632E387E7E45"
  },
  "volume": "11",
  "article_number": "1254905"
}