{
  "category": {
    "code": "ACADEMICREVIEW",
    "name": {
      "en": "Academic literature review"
    }
  },
  "channel": {
    "title": "Tidsskrift for Norsk psykologforening (Psykologtidsskriftet)"
  },
  "contributors": {
    "url": "https://api.cristin.no/v2/results/835907/contributors",
    "count": 3,
    "preview": [
      {
        "first_name": "Bjørn",
        "surname": "Lau"
      },
      {
        "first_name": "Live Bakke",
        "surname": "Finne"
      },
      {
        "first_name": "Mona",
        "surname": "Berthelsen"
      }
    ]
  },
  "cristin_result_id": "835907",
  "nva_result_id": "0198cc5d9849-50482f05-95bc-4cc6-ab86-4affc1d53c48",
  "created": {
    "date": "2025-08-21T11:22:22.000Z"
  },
  "last_modified": {
    "date": "2025-10-13T17:39:40.000Z"
  },
  "original_language": "nb",
  "summary": {
    "nb": "The research literature on the involuntary unemployed indicates that work has a number of beneficial effects on mental health. Nonetheless, certain psychosocial factors seem to increase the risk for employees to develop poor mental health, particularly anxiety and depressive symptoms: High job demands and low degree of influence and social support, or low degree of appreciation, career opportunities and job security are considered as risk factors in this respect. In addition, there is still a need to identify work environment factors that prevent people with poor mental health from falling into long-term sickness and disability pension. So far, to our knowledge, only one study has been done in this field. It indicated that good leadership serves as protection against long-term sick leave among employees with moderate depression symptoms."
  },
  "title": {
    "nb": "Deltakelse i arbeidslivet : helsefremmende eller en risiko for utvikling av dårlig mental helse?"
  },
  "year_published": "2011",
  "url": "https://api.cristin.no/v2/results/835907",
  "journal": {
    "cristin_journal_id": "9AA97551-C498-4335-A436-1612A6D9A322",
    "name": "Tidsskrift for Norsk psykologforening (Psykologtidsskriftet)",
    "international_standard_numbers": [
      {
        "type": "printed",
        "value": "0332-6470"
      },
      {
        "type": "electronic",
        "value": "2703-9528"
      }
    ],
    "nvi_level": "1",
    "external_url": "https://kanalregister.hkdir.no/publiseringskanaler/info/tidsskrift?pid=9AA97551-C498-4335-A436-1612A6D9A322"
  },
  "volume": "48",
  "issue": "8",
  "pages": {
    "from": "745",
    "to": "750"
  }
}