{
  "category": {
    "code": "ARTICLEPOPULAR",
    "name": {
      "en": "Popular scientific article"
    }
  },
  "channel": {
    "title": "Fabian Review"
  },
  "contributors": {
    "url": "https://api.cristin.no/v2/results/1022898/contributors",
    "count": 3,
    "preview": [
      {
        "first_name": "Dag Einar",
        "surname": "Thorsen"
      },
      {
        "first_name": "Nikolai",
        "surname": "Brandal"
      },
      {
        "first_name": "Øivind",
        "surname": "Bratberg"
      }
    ]
  },
  "cristin_result_id": "1022898",
  "nva_result_id": "0198cc5a7c4e-148243bd-dbab-43fb-bfce-339a3f10e634",
  "created": {
    "date": "2025-08-21T11:18:58.000Z"
  },
  "last_modified": {
    "date": "2025-10-13T17:20:38.000Z"
  },
  "date_published": "2013-04-08T00:00:00.000Z",
  "links": [
    {
      "url_type": "FULLTEKST",
      "url": "http://www.fabians.org.uk/utopia-sustained-the-nordic-model-of-social-democracy/"
    }
  ],
  "original_language": "en",
  "title": {
    "en": "Utopia sustained: The Nordic model of social democracy"
  },
  "year_published": "2013",
  "url": "https://api.cristin.no/v2/results/1022898",
  "journal": {
    "cristin_journal_id": "94F711B2-C7A1-4C2A-9215-0A01C3305A90",
    "name": "Fabian Review",
    "external_url": "https://kanalregister.hkdir.no/publiseringskanaler/info/nvakanal?pid=94F711B2-C7A1-4C2A-9215-0A01C3305A90"
  }
}