{
  "category": {
    "code": "ACADEMICREVIEW",
    "name": {
      "en": "Academic literature review"
    }
  },
  "channel": {
    "title": "The BMJ"
  },
  "contributors": {
    "url": "https://api.cristin.no/v2/results/1367622/contributors",
    "count": 8,
    "preview": [
      {
        "first_name": "Dagfinn",
        "surname": "Aune"
      },
      {
        "first_name": "Abhijit",
        "surname": "Sen"
      },
      {
        "first_name": "Manya",
        "surname": "Prasad"
      },
      {
        "first_name": "Teresa",
        "surname": "Norat"
      },
      {
        "first_name": "Imre",
        "surname": "Janszky"
      },
      {
        "first_name": "Serena",
        "surname": "Tonstad"
      }
    ]
  },
  "cristin_result_id": "1367622",
  "nva_result_id": "0198cc64bb39-7d54fc3c-c041-43dd-a71d-83627866ef96",
  "created": {
    "date": "2025-08-21T11:30:10.000Z"
  },
  "import_sources": [
    {
      "source_name": "SCOPUS",
      "source_reference_id": "2-s2.0-84969776591"
    }
  ],
  "last_modified": {
    "date": "2025-10-11T22:24:46.000Z"
  },
  "links": [
    {
      "url_type": "DOI",
      "url": "https://doi.org/10.1136/bmj.i2156"
    },
    {
      "url_type": "FULLTEKST",
      "url": "http://www.bmj.com/content/bmj/353/bmj.i2156.full.pdf"
    }
  ],
  "original_language": "en",
  "title": {
    "en": "BMI and all cause mortality: Systematic review and non-linear dose-response meta-analysis of 230 cohort studies with 3.74 million deaths among 30.3 million participants"
  },
  "year_published": "2016",
  "url": "https://api.cristin.no/v2/results/1367622",
  "journal": {
    "cristin_journal_id": "C74A8077-638A-410D-B614-C63E06D012F7",
    "name": "The BMJ",
    "international_standard_numbers": [
      {
        "type": "electronic",
        "value": "1756-1833"
      }
    ],
    "nvi_level": "2",
    "external_url": "https://kanalregister.hkdir.no/publiseringskanaler/info/tidsskrift?pid=C74A8077-638A-410D-B614-C63E06D012F7"
  },
  "volume": "353"
}