{
  "category": {
    "code": "MEDIAINTERVIEW",
    "name": {
      "en": "Interview"
    }
  },
  "contributors": {
    "url": "https://api.cristin.no/v2/results/2052280/contributors",
    "count": 1,
    "preview": [
      {
        "first_name": "Kjetil",
        "surname": "Tronvoll"
      }
    ]
  },
  "cristin_result_id": "2052280",
  "nva_result_id": "0198cc5f2041-74ab3f1a-ed47-458c-8aaf-0fa3fc7afd84",
  "created": {
    "date": "2025-08-21T11:24:03.000Z"
  },
  "last_modified": {
    "date": "2025-10-13T14:25:20.000Z"
  },
  "date_published": "2022-09-15T00:00:00.000Z",
  "links": [
    {
      "url_type": "FULLTEKST",
      "url": "https://english.alaraby.co.uk/analysis/ethiopias-return-war-there-truce-horizon"
    }
  ],
  "original_language": "en",
  "title": {
    "en": "Ethiopia's return to war: Is there a truce on the horizon?"
  },
  "year_published": "2022",
  "url": "https://api.cristin.no/v2/results/2052280",
  "media_type": {
    "code": "TIDSSKRIFT",
    "code_name": {
      "en": "Journal"
    }
  },
  "place": "The New Arab"
}