{
  "category": {
    "code": "ARTICLEFEATURE",
    "name": {
      "en": "Feature article"
    }
  },
  "channel": {},
  "contributors": {
    "url": "https://api.cristin.no/v2/results/481556/contributors",
    "count": 1,
    "preview": [
      {
        "first_name": "Kjetil",
        "surname": "Tronvoll"
      }
    ]
  },
  "cristin_result_id": "481556",
  "nva_result_id": "0198cc4d1bed-421fb8ab-b794-4e61-ab26-c7e49d7033b4",
  "created": {
    "date": "2025-08-21T11:04:22.000Z"
  },
  "last_modified": {
    "date": "2025-10-14T01:53:57.000Z"
  },
  "date_published": "2008-08-05T00:00:00.000Z",
  "original_language": "nb",
  "title": {
    "nb": "FN fiasko"
  },
  "year_published": "2008",
  "url": "https://api.cristin.no/v2/results/481556",
  "journal": {}
}