{
  "category": {
    "code": "CHAPTERACADEMIC",
    "name": {
      "en": "Academic chapter/article/Conference paper"
    }
  },
  "contributors": {
    "url": "https://api.cristin.no/v2/results/74735/contributors",
    "count": 1,
    "preview": [
      {
        "first_name": "Kjetil",
        "surname": "Tronvoll"
      }
    ]
  },
  "cristin_result_id": "74735",
  "nva_result_id": "0198cc7a6c56-6a322b0d-ff3d-440d-b34e-4c8a50900bcd",
  "created": {
    "date": "2025-08-21T11:53:51.000Z"
  },
  "last_modified": {
    "date": "2025-10-14T01:12:10.000Z"
  },
  "original_language": "en",
  "title": {
    "en": "Conclusion: Democracy advanced or restricted?"
  },
  "year_published": "2000",
  "url": "https://api.cristin.no/v2/results/74735",
  "part_of": {
    "url": "https://api.cristin.no/v2/results/0198cc40cdf1-fe6988dd-7f2d-44e9-97a2-9162759a421c"
  }
}