{
  "category": {
    "code": "CHAPTERACADEMIC",
    "name": {
      "en": "Academic chapter/article/Conference paper"
    }
  },
  "contributors": {
    "url": "https://api.cristin.no/v2/results/1049724/contributors",
    "count": 1,
    "preview": [
      {
        "first_name": "Henrik",
        "surname": "Syse"
      }
    ]
  },
  "cristin_result_id": "1049724",
  "nva_result_id": "0198cc6b0874-5e7da509-d356-4f63-9f44-da70c44496e4",
  "created": {
    "date": "2025-08-21T11:37:03.000Z"
  },
  "last_modified": {
    "date": "2025-10-13T13:27:35.000Z"
  },
  "original_language": "nb",
  "title": {
    "nb": "Thomas Aquinas – kristentro og fornuft i det politiske samfunn"
  },
  "year_published": "2013",
  "url": "https://api.cristin.no/v2/results/1049724",
  "part_of": {
    "url": "https://api.cristin.no/v2/results/0198cc647301-7c71054b-6014-44d6-bc07-2fb9c35ab0ef"
  },
  "pages": {
    "from": "179",
    "to": "204"
  }
}