{
  "category": {
    "code": "REPORT",
    "name": {
      "en": "Report"
    }
  },
  "channel": {
    "title": "Universitetet i Oslo"
  },
  "contributors": {
    "url": "https://api.cristin.no/v2/results/316068/contributors",
    "count": 2,
    "preview": [
      {
        "first_name": "Jemima",
        "surname": "García-Godos"
      },
      {
        "first_name": "Henrik",
        "surname": "Wiig"
      }
    ]
  },
  "cristin_result_id": "316068",
  "nva_result_id": "0198cc8f1bb4-75ea05d4-1a4d-4224-8ed9-85610065a8b6",
  "created": {
    "date": "2025-08-21T12:16:27.000Z"
  },
  "last_modified": {
    "date": "2025-10-13T21:49:58.000Z"
  },
  "links": [
    {
      "url_type": "FULLTEKST",
      "url": "http://www.regjeringen.no/upload/kilde/ud/nyh/2006/0104/ddd/word/286966-analysis_on_latin_america.doc"
    }
  ],
  "original_language": "en",
  "title": {
    "en": "An Analysis of the Political and Socio-Economic Situation in Latin America. Background Document for the Working Group for Latin America, Ministry of Foreign Affairs, Norway"
  },
  "year_published": "2006",
  "url": "https://api.cristin.no/v2/results/316068",
  "number_of_pages": "78",
  "publisher": {
    "name": "Universitetet i Oslo",
    "url": "https://kanalregister.hkdir.no/publiseringskanaler/info/forlag?pid=A04A15C5-1B21-46BB-BC1D-AA4EF9B6DEB9"
  }
}