{
  "category": {
    "code": "ARTICLEPOPULAR",
    "name": {
      "en": "Popular scientific article"
    }
  },
  "channel": {
    "title": "News Deeply"
  },
  "contributors": {
    "url": "https://api.cristin.no/v2/results/1403557/contributors",
    "count": 1,
    "preview": [
      {
        "first_name": "Andreas",
        "surname": "Østhagen"
      }
    ]
  },
  "cristin_result_id": "1403557",
  "nva_result_id": "0198cc5c26f2-12ea6a66-e4a0-4963-b6fa-c1960dadedff",
  "created": {
    "date": "2025-08-21T11:20:48.000Z"
  },
  "last_modified": {
    "date": "2025-10-14T01:58:19.000Z"
  },
  "date_published": "2016-11-11T00:00:00.000Z",
  "original_language": "en",
  "title": {
    "en": "There’s More to Worry About Than One Cruise Ship in the Arctic"
  },
  "year_published": "2016",
  "url": "https://api.cristin.no/v2/results/1403557",
  "journal": {
    "cristin_journal_id": "E5D0D610-03F9-40B8-9432-3A07041DEC2A",
    "name": "News Deeply",
    "external_url": "https://kanalregister.hkdir.no/publiseringskanaler/info/nvakanal?pid=E5D0D610-03F9-40B8-9432-3A07041DEC2A"
  }
}