{
  "category": {
    "code": "LECTURE",
    "name": {
      "en": "Lecture"
    }
  },
  "contributors": {
    "url": "https://api.cristin.no/v2/results/2063419/contributors",
    "count": 1,
    "preview": [
      {
        "first_name": "Andreas",
        "surname": "Østhagen"
      }
    ]
  },
  "cristin_result_id": "2063419",
  "nva_result_id": "0198cc4740d8-8d9bf0ac-6408-4e39-8af1-4c3b1e343ef8",
  "created": {
    "date": "2025-08-21T10:57:58.000Z"
  },
  "funding_sources": [
    {
      "funding_source_code": "FNI",
      "project_code": "531",
      "funding_source_name": {
        "nb": "Fridtjof Nansens institutt",
        "en": "Fridtjof Nansen Institute"
      }
    },
    {
      "funding_source_code": "FNI",
      "project_code": "513",
      "funding_source_name": {
        "nb": "Fridtjof Nansens institutt",
        "en": "Fridtjof Nansen Institute"
      }
    },
    {
      "funding_source_code": "FNI",
      "project_code": "515",
      "funding_source_name": {
        "nb": "Fridtjof Nansens institutt",
        "en": "Fridtjof Nansen Institute"
      }
    },
    {
      "funding_source_code": "NFR",
      "project_code": "314457",
      "funding_source_name": {
        "nb": "Norges forskningsråd",
        "en": "Research Council of Norway (RCN)"
      }
    },
    {
      "funding_source_code": "NFR",
      "project_code": "315163",
      "funding_source_name": {
        "nb": "Norges forskningsråd",
        "en": "Research Council of Norway (RCN)"
      }
    }
  ],
  "last_modified": {
    "date": "2025-10-11T17:37:17.000Z"
  },
  "original_language": "en",
  "title": {
    "en": "Arctic Geopolitics? What, where and why"
  },
  "year_published": "2022",
  "url": "https://api.cristin.no/v2/results/2063419",
  "event": {
    "name": "Arctic Connections 2022",
    "location": "Roma",
    "date_from": "2022-10-18T00:00:00.000Z",
    "arranged_by": {
      "name": "SIOI"
    }
  }
}