{
  "category": {
    "code": "ACADEMICLECTURE",
    "name": {
      "en": "Academic lecture"
    }
  },
  "contributors": {
    "url": "https://api.cristin.no/v2/results/2068285/contributors",
    "count": 1,
    "preview": [
      {
        "first_name": "Andreas",
        "surname": "Østhagen"
      }
    ]
  },
  "cristin_result_id": "2068285",
  "nva_result_id": "0198cc6923cc-5707b325-ca53-45d8-a017-9d2470742064",
  "created": {
    "date": "2025-08-21T11:34:59.000Z"
  },
  "funding_sources": [
    {
      "funding_source_code": "FNI",
      "project_code": "531",
      "funding_source_name": {
        "nb": "Fridtjof Nansens institutt",
        "en": "Fridtjof Nansen Institute"
      }
    },
    {
      "funding_source_code": "FNI",
      "project_code": "513",
      "funding_source_name": {
        "nb": "Fridtjof Nansens institutt",
        "en": "Fridtjof Nansen Institute"
      }
    },
    {
      "funding_source_code": "FNI",
      "project_code": "515",
      "funding_source_name": {
        "nb": "Fridtjof Nansens institutt",
        "en": "Fridtjof Nansen Institute"
      }
    },
    {
      "funding_source_code": "NFR",
      "project_code": "314457",
      "funding_source_name": {
        "nb": "Norges forskningsråd",
        "en": "Research Council of Norway (RCN)"
      }
    },
    {
      "funding_source_code": "NFR",
      "project_code": "315163",
      "funding_source_name": {
        "nb": "Norges forskningsråd",
        "en": "Research Council of Norway (RCN)"
      }
    }
  ],
  "last_modified": {
    "date": "2025-10-12T19:01:19.000Z"
  },
  "original_language": "en",
  "title": {
    "en": "Comparing Bering Sea and Barents Sea regions"
  },
  "year_published": "2022",
  "url": "https://api.cristin.no/v2/results/2068285",
  "event": {
    "name": "Bering Strait: Navigation and Conservation in Times of Conflict",
    "date_from": "2022-11-02T00:00:00.000Z",
    "arranged_by": {
      "name": "Harvard Belfer Center and Wilson Center"
    }
  }
}