{
  "category": {
    "code": "MEDIAINTERVIEW",
    "name": {
      "en": "Interview"
    }
  },
  "contributors": {
    "url": "https://api.cristin.no/v2/results/2156979/contributors",
    "count": 1,
    "preview": [
      {
        "first_name": "Andreas",
        "surname": "Østhagen"
      }
    ]
  },
  "cristin_result_id": "2156979",
  "nva_result_id": "0198cc6c5096-76752043-0233-4a38-aef9-a6a38ef5095f",
  "created": {
    "date": "2025-08-21T11:38:27.000Z"
  },
  "funding_sources": [
    {
      "funding_source_code": "FNI",
      "project_code": "513",
      "funding_source_name": {
        "nb": "Fridtjof Nansens institutt",
        "en": "Fridtjof Nansen Institute"
      }
    },
    {
      "funding_source_code": "FNI",
      "project_code": "547",
      "funding_source_name": {
        "nb": "Fridtjof Nansens institutt",
        "en": "Fridtjof Nansen Institute"
      }
    },
    {
      "funding_source_code": "NFR",
      "project_code": "314457",
      "funding_source_name": {
        "nb": "Norges forskningsråd",
        "en": "Research Council of Norway (RCN)"
      }
    }
  ],
  "last_modified": {
    "date": "2025-10-13T18:39:12.000Z"
  },
  "date_published": "2023-05-27T00:00:00.000Z",
  "original_language": "nb",
  "title": {
    "nb": "Verdens største krigsskip i Oslo: – Utfordringen er å avskrekke, men samtidig ikke provosere (World’s largest warship in Oslo: - The challenge is to deter but also not provoke)"
  },
  "year_published": "2023",
  "url": "https://api.cristin.no/v2/results/2156979",
  "media_type": {
    "code": "INTERNETT",
    "code_name": {
      "en": "Internet"
    }
  },
  "place": "Altinget"
}