{
  "category": {
    "code": "POSTER",
    "name": {
      "en": "Poster"
    }
  },
  "contributors": {
    "url": "https://api.cristin.no/v2/results/1997572/contributors",
    "count": 4,
    "preview": [
      {
        "first_name": "Siri",
        "surname": "Weider"
      },
      {
        "first_name": "Tora",
        "surname": "Thorsrud"
      },
      {
        "first_name": "Linda",
        "surname": "Thorsen"
      },
      {
        "first_name": "Anna Maria Camilla Lindvall",
        "surname": "Dahlgren"
      }
    ]
  },
  "cristin_result_id": "1997572",
  "nva_result_id": "0198cc95dabc-8133bbf0-2bf7-48a0-8d7b-4d7f8090b17d",
  "created": {
    "date": "2025-08-21T12:23:49.000Z"
  },
  "last_modified": {
    "date": "2025-10-13T11:04:08.000Z"
  },
  "original_language": "nb",
  "summary": {
    "nb": "Spiseforstyrrelser (SF) er komplekse psykiske lidelser med relativt dårlig prognose. Kognitive utfordringer, særlig eksekutive vansker og svak sentral koherens er hyppig forekommende hos denne pasientgruppen. Disse utfordringene kan sannsynligvis føre til økt sårbarhet for utviklingen av SF, komplisere behandlingsforløpet og virke som opprettholdende faktorer. Disse utfordringene er imidlertid sjelden belyst i ordinær terapi. \r\n\r\nVi ønsker å undersøke effekten av metakognitiv trening (Cognitive Remediation Therapy; CRT) for pasienter med spiseforstyrrelser og samtidige kognitive vansker. I tillegg vil vi undersøke kognitiv funksjon og assosiasjoner mellom kognitiv funksjon, symptomer og mål på aktivitet og søvn både ved baseline og ved oppfølging."
  },
  "title": {
    "nb": "Transdiagnostisk kognitiv trening for pasienter med spiseforstyrrelser: En randomisert kontrollert studie"
  },
  "year_published": "2022",
  "url": "https://api.cristin.no/v2/results/1997572",
  "event": {
    "name": "Regional digital forskningskonferanse i Helse Midt-Norge RHF ",
    "location": "Digitalt",
    "date_from": "2022-02-09T00:00:00.000Z",
    "date_to": "2022-02-09T00:00:00.000Z",
    "arranged_by": {
      "name": "Helse Midt-Norge RHF"
    }
  }
}