{
  "category": {
    "code": "ACADEMICLECTURE",
    "name": {
      "en": "Academic lecture"
    }
  },
  "contributors": {
    "url": "https://api.cristin.no/v2/results/2123645/contributors",
    "count": 1,
    "preview": [
      {
        "first_name": "Anna Maria Camilla Lindvall",
        "surname": "Dahlgren"
      }
    ]
  },
  "cristin_result_id": "2123645",
  "nva_result_id": "0198cc8b19af-74551d27-9d83-4e69-a9c9-5de6e9d54430",
  "created": {
    "date": "2025-08-21T12:12:04.000Z"
  },
  "last_modified": {
    "date": "2025-10-13T17:55:45.000Z"
  },
  "original_language": "nb",
  "title": {
    "nb": "Forekomst av spiseforstyrrelser hos ungdom – en epidemiologisk studie"
  },
  "year_published": "2022",
  "url": "https://api.cristin.no/v2/results/2123645",
  "event": {
    "name": "Fagmøte",
    "location": "Oslo",
    "date_from": "2022-02-21T06:00:00.000Z",
    "date_to": "2022-02-22T05:00:00.000Z",
    "arranged_by": {
      "name": "Mental Helse"
    }
  }
}